pyCFE/__init__.py
pyCFE/biller/__init__.py
pyCFE/biller/biller.py
pyCFE/biller/cliente.py
pyCFE/common/__init__.py
pyCFE/common/documento.py
pyCFE/common/empresa.py
pyCFE/common/servidor.py
pyCFE/efactura/__init__.py
pyCFE/efactura/cliente.py
pyCFE/efactura/efactura.py
pyCFE/facturaexpress/__init__.py
pyCFE/facturaexpress/cliente.py
pyCFE/facturaexpress/facturaexpress.py
pycfe-0.6.0.dist-info/licenses/LICENSE
pycfe-0.6.0.dist-info/METADATA
pycfe-0.6.0.dist-info/WHEEL
pycfe-0.6.0.dist-info/entry_points.txt
pycfe-0.6.0.dist-info/top_level.txt
pycfe-0.6.0.dist-info/RECORD
