Metadata-Version: 2.4
Name: pyCFE
Version: 0.6.0
Summary: Facturacion Electronica Uruguaya
Home-page: 
Author: Alex Cuellar
Author-email: acuellar@grupoyacck.com
Maintainer: Alex Cuellar
Maintainer-email: acuellar@grupoyacck.com
License: GPLv3
Keywords: pyCFE
Classifier: Programming Language :: Python :: 3
Classifier: Programming Language :: Python :: 3.5
Classifier: Programming Language :: Python :: 3.6
Classifier: Programming Language :: Python :: 3.7
Classifier: Programming Language :: Python :: 3.8
Classifier: Programming Language :: Python :: 3.9
Classifier: Programming Language :: Python :: 3.10
License-File: LICENSE
Requires-Dist: lxml
Requires-Dist: requests
Requires-Dist: zeep
Dynamic: author
Dynamic: author-email
Dynamic: classifier
Dynamic: description
Dynamic: description-content-type
Dynamic: keywords
Dynamic: license
Dynamic: license-file
Dynamic: maintainer
Dynamic: maintainer-email
Dynamic: requires-dist
Dynamic: summary
